<suitelet scriptid="customscript_dt_starter_kit">
  <description></description>
  <isinactive>F</isinactive>
  <name>DT | Starter Kit</name>
  <notifyadmins>F</notifyadmins>
  <notifyemails></notifyemails>
  <notifyowner>T</notifyowner>
  <notifyuser>F</notifyuser>
  <scriptfile>[/SuiteScripts/starter-kit/datatek-starter-kit-suitelet.js]</scriptfile>
  <scriptdeployments>
    <scriptdeployment scriptid="customdeploy_dt_starter_kit">
      <allemployees>F</allemployees>
      <allpartners>F</allpartners>
      <allroles>T</allroles>
      <audslctrole></audslctrole>
      <eventtype></eventtype>
      <isdeployed>T</isdeployed>
      <isonline>F</isonline>
      <loglevel>DEBUG</loglevel>
      <runasrole></runasrole>
      <status>TESTING</status>
      <title>DT | Starter Kit</title>
    </scriptdeployment>
  </scriptdeployments>
</suitelet>